[
    {
        "content": "<p>Hello! Just a reminder, tomorrow we have our documentation working group meeting. <a href=\"https://github.com/gdcc/www.gdcc.io/blob/main/source/working-groups/documentation.md\">https://github.com/gdcc/www.gdcc.io/blob/main/source/working-groups/documentation.md</a> </p>\n<p>If you have any topics to add to the agenda, please do so here: <a href=\"https://docs.google.com/document/d/1dX8ktajVsRDk-MDF-yHWV0f4vIe8U3DWrSzIerVGlF8/edit?usp=sharing\">https://docs.google.com/document/d/1dX8ktajVsRDk-MDF-yHWV0f4vIe8U3DWrSzIerVGlF8/edit?usp=sharing</a></p>",
        "id": 545323366,
        "sender_full_name": "Omer M Fahim",
        "timestamp": 1760621534
    },
    {
        "content": "<p>I'm at a conference this week, so I'll be skipping this one.</p>",
        "id": 545475229,
        "sender_full_name": "Dieuwertje Bloemen",
        "timestamp": 1760669042
    },
    {
        "content": "<p>not enough participants joined this months meeting - lets try again next month.</p>",
        "id": 545660850,
        "sender_full_name": "Omer M Fahim",
        "timestamp": 1760727195
    }
]