[
    {
        "content": "<p>This topic was moved here from <a class=\"stream-topic\" data-stream-id=\"379673\" href=\"/#narrow/channel/379673-dev/topic/Croissant\">#dev &gt; Croissant</a> by <span class=\"user-mention silent\" data-user-id=\"598112\">Philip Durbin 🚀</span>.</p>",
        "id": 564714021,
        "sender_full_name": "Notification Bot",
        "timestamp": 1766156077
    },
    {
        "content": "<p>I move this topic from <a class=\"stream\" data-stream-id=\"379673\" href=\"/#narrow/channel/379673-dev\">#dev</a> because Croissant is in production now.</p>",
        "id": 564714156,
        "sender_full_name": "Philip Durbin 🚀",
        "timestamp": 1766156107
    }
]