[
    {
        "content": "<p>Like Dataverse, it's possible to run Zulip headless, as only an API. There's a new <a href=\"https://chat.zulip.org/#narrow/channel/2-general/topic/Q.26A.20.28idea.29.3A.20custom.20clients/near/2462772\">custom clients</a> topic over at CZO (Chat.Zulip.Org) about this.</p>",
        "id": 600638618,
        "sender_full_name": "Philip Durbin 🚀",
        "timestamp": 1780653325
    },
    {
        "content": "<p>It was kicked off my the creator of this custom Zulip client: <a href=\"https://github.com/showell/angry-cat\">https://github.com/showell/angry-cat</a></p>",
        "id": 600638739,
        "sender_full_name": "Philip Durbin 🚀",
        "timestamp": 1780653365
    }
]