[
    {
        "content": "<p>We recently upgraded to v6.4 and Re-indexing got stuck 3-4 times on 2 different datasets which are really huge. We run re-index on a separate server which is not part of Production workload. While re-indexing was stuck Payara server got stuck too and app was unavailable. It ran for hours and 1 time Payara server crashed and restarted with OutofMemory error and other time Payara server did not come back after crash.  <br>\nI had to manually set <code>indextime</code> of these 2 datasets in DB to proceed with Re-index of other datasets. Last time on 6.2 upgrade it took a while to re-index but we did not run into issue with frozen server.<br>\nFirst dataset has 1057 files with size 321G on disk<br>\nSecond dataset 2872 files with 84G size</p>",
        "id": 496425661,
        "sender_full_name": "Bikram",
        "timestamp": 1738098918
    },
    {
        "content": "<p>Did you try increasing the memory for your system, Bikram - did the indexing finish eventually?</p>",
        "id": 497086528,
        "sender_full_name": "Steve Baroti",
        "timestamp": 1738356823
    },
    {
        "content": "<p>System has 32GB memory, I think should be enough. It did not finish and got stuck. I had to manually update indextime in DB to proceed with other datasets.</p>",
        "id": 497086997,
        "sender_full_name": "Bikram",
        "timestamp": 1738357018
    },
    {
        "content": "<p>Bikram, go ahead and try 64GB, and please keep us posted! <span aria-label=\"fingers crossed\" class=\"emoji emoji-1f91e\" role=\"img\" title=\"fingers crossed\">:fingers_crossed:</span></p>",
        "id": 497090608,
        "sender_full_name": "Steve Baroti",
        "timestamp": 1738358512
    },
    {
        "content": "<p><span class=\"user-mention\" data-user-id=\"719882\">@Bikram</span> thanks for opening <a href=\"https://github.com/IQSS/dataverse/issues/11284\">#11284</a> about this.</p>",
        "id": 501885121,
        "sender_full_name": "Philip Durbin 🚀",
        "timestamp": 1740508902
    },
    {
        "content": "<p><span class=\"user-mention\" data-user-id=\"719882\">@Bikram</span> what's Payara's Xmx value?</p>",
        "id": 502028791,
        "sender_full_name": "Don Sizemore",
        "timestamp": 1740571058
    },
    {
        "content": "<p>Hi <span class=\"user-mention\" data-user-id=\"626369\">@Don Sizemore</span>, Its <code>-Xmx24576m</code></p>",
        "id": 502047597,
        "sender_full_name": "Bikram",
        "timestamp": 1740576772
    }
]