[
    {
        "content": "<p>After upgrading Docker to v29, DMP v0.46.0 no longer worked for me. Upgrading with <code>-Dfabric8-dmp.version=0.48.0</code> healed that temporarily on my machine. (In the release notes they state that due to an API change in Docker you need the latest plugin). Anyone willing to test this newer version on their machines? (Lookign at y'all, troubled Mac Users)</p>",
        "id": 562463403,
        "sender_full_name": "Oliver Bertuch",
        "timestamp": 1765199635
    },
    {
        "content": "<p>I appreciate the heads up on this. I'm heads down on something else right now but I added it to agenda for the next container meeting.</p>",
        "id": 562696749,
        "sender_full_name": "Philip Durbin 🚀",
        "timestamp": 1765290012
    },
    {
        "content": "<p><span class=\"user-mention\" data-user-id=\"1007626\">@Stephen Kraffmiller</span> just mentioned he got a new Mac laptop and Docker is working. That's a good sign.</p>",
        "id": 571942710,
        "sender_full_name": "Philip Durbin 🚀",
        "timestamp": 1770219207
    },
    {
        "content": "<p>Sounds like more folks are hitting this snag. Should I do a small PR to upgrade the version?</p>",
        "id": 572129363,
        "sender_full_name": "Oliver Bertuch",
        "timestamp": 1770292932
    },
    {
        "content": "<p>Sure, onwards and upwards! Thanks!</p>",
        "id": 572129692,
        "sender_full_name": "Philip Durbin 🚀",
        "timestamp": 1770293000
    },
    {
        "content": "<p>Thanks, <span class=\"user-mention\" data-user-id=\"598183\">@Oliver Bertuch</span> , it does indeed work with</p>\n<p><code>mvn -Pct -Dfabric8-dmp.version=0.48.0 docker:run</code></p>",
        "id": 572140751,
        "sender_full_name": "Balázs Pataki",
        "timestamp": 1770296229
    },
    {
        "content": "<p>I'll merge both discussions <span aria-label=\"smiley\" class=\"emoji emoji-1f603\" role=\"img\" title=\"smiley\">:smiley:</span></p>",
        "id": 572141226,
        "sender_full_name": "Oliver Bertuch",
        "timestamp": 1770296380
    },
    {
        "content": "<p>12 messages were moved here from <a class=\"stream-topic\" data-stream-id=\"375812\" href=\"/#narrow/channel/375812-containers/topic/Regression.20or.20is.20it.20just.20me.3F\">#containers &gt; Regression or is it just me?</a> by <span class=\"user-mention silent\" data-user-id=\"598183\">Oliver Bertuch</span>.</p>",
        "id": 572141330,
        "sender_full_name": "Notification Bot",
        "timestamp": 1770296404
    },
    {
        "content": "<p>Here's the PR: <a href=\"https://github.com/IQSS/dataverse/issues/12146\">#12146</a> I didn't bother with creating an issue first for this very small fix.</p>",
        "id": 572143023,
        "sender_full_name": "Oliver Bertuch",
        "timestamp": 1770296870
    },
    {
        "content": "<p>Merged! Thanks, gentlemen!</p>",
        "id": 572161727,
        "sender_full_name": "Philip Durbin 🚀",
        "timestamp": 1770301320
    }
]